{
    "patient_types": [
        {"type": "A", "diagnosis": "A1", "operation_time_mean": null, "operation_time_std": null, "nursing_time_mean": 4, "nursing_time_std": 0.5, "complication_prob": 0.01, "arrival_rate": "random.uniform(0,1)"},
        {"type": "A", "diagnosis": "A2", "operation_time_mean": 1, "operation_time_std": 0.25, "nursing_time_mean": 8, "nursing_time_std": 2, "complication_prob": 0.01, "arrival_rate": "random.uniform(0,1)"},
        {"type": "A", "diagnosis": "A3", "operation_time_mean": 2, "operation_time_std": 0.5, "nursing_time_mean": 16, "nursing_time_std": 2, "complication_prob": 0.02, "arrival_rate": "random.uniform(0,1)"},
        {"type": "A", "diagnosis": "A4", "operation_time_mean": 4, "operation_time_std": 1, "nursing_time_mean": 16, "nursing_time_std": 2, "complication_prob": 0.02, "arrival_rate": "random.uniform(0,1)"},
        {"type": "B", "diagnosis": "B1", "operation_time_mean": null, "operation_time_std": null, "nursing_time_mean": 8, "nursing_time_std": 2, "complication_prob": 0.001, "arrival_rate": "random.uniform(0,1)"},
        {"type": "B", "diagnosis": "B2", "operation_time_mean": null, "operation_time_std": null, "nursing_time_mean": 16, "nursing_time_std": 2, "complication_prob": 0.01, "arrival_rate": "random.uniform(0,1)"},
        {"type": "B", "diagnosis": "B3", "operation_time_mean": 4, "operation_time_std": 1, "nursing_time_mean": 16, "nursing_time_std": 4, "complication_prob": 0.02, "arrival_rate": "random.uniform(0,1)"},
        {"type": "B", "diagnosis": "B4", "operation_time_mean": 4, "operation_time_std": 1, "nursing_time_mean": 16, "nursing_time_std": 4, "complication_prob": 0.02, "arrival_rate": "random.uniform(0,1)"},
        {"type": "EM", "diagnosis": "ER", "operation_time_mean": null, "operation_time_std": null, "nursing_time_mean": null, "nursing_time_std": null, "complication_prob": null, "arrival_rate": "random.expovariate(1)"}
    ]
}
